newpyproj/__init__.py
newpyproj/__main__.py
newpyproj/newpyproj.py
newpyproj/support.py
newpyproj-0.0.3.dist-info/METADATA
newpyproj-0.0.3.dist-info/WHEEL
newpyproj-0.0.3.dist-info/top_level.txt
newpyproj-0.0.3.dist-info/RECORD
