Metadata-Version: 2.1
Name: newpyproj
Version: 0.0.3
Summary: Automatically creates a new python project folder
Home-page: https://github.com/rafxel/newpyproj/
Author: Rafael Leite Paulo
Author-email: rafael@leite.org
License: UNKNOWN
Keywords: TEMPLATE,AUTOMATION,PROJECT,STRUCTURE,PACKAGE
Platform: UNKNOWN
Classifier: Programming Language :: Python :: 3
Classifier: License :: OSI Approved :: MIT License
Classifier: Operating System :: OS Independent
Requires-Python: >=3.6
Requires-Dist: pytest
